<?xml version="1.0" encoding="utf-8"?>
<odoo>
    <record id="view_pedidos_tienda_orden_compra_form" model="ir.ui.view">
        <field name="name">pedidos.tienda.orden_compra.form</field>
        <field name="model">pedidos_tienda.orden_compra</field>
        <field name="arch" type="xml">
            <form string="Productos">
                <field name="productos_ids"/>
                <footer>
                    <button name="generar" string="Generar" type="object" class="oe_highlight"/>
                    or
                    <button string="Cancel" class="oe_link" special="cancel"/>
                </footer>
            </form>
        </field>
    </record>

   <record id="pedidos_tienda_producto_tree" model="ir.ui.view">
        <field name="name">pedidos_tienda.producto.tree</field>
        <field name="model">pedidos_tienda.producto</field>
        <field name="arch" type="xml">
            <tree editable="bottom">
                <field name="product_id"/>
                <field name="uom_id"/>
                <field name="qty"/>
            </tree>
        </field>
    </record>

    <record id="pedidos_tienda.action_window_orden_compra" model="ir.actions.act_window">
        <field name="name">Generar ordenes compras</field>
        <field name="res_model">pedidos_tienda.orden_compra</field>
        <field name="view_type">form</field>
        <field name="view_mode">form</field>
        <field name="target">new</field>
    </record>

    <menuitem name="Generar ordenes compras" id="pedidos_tienda.menu_orden_compra" parent="purchase.menu_procurement_management"
              action="pedidos_tienda.action_window_orden_compra"/>

</odoo>
